{
    "Coordinate3D": {
        "definition": null,
        "related_terms": [
            null
        ],
        "standards": [
            null
        ],
        "date_added": "14/10/2020",
        "date_deprecated": null,
        "version": null,
        "children": {
            "yCoordinate": {
                "definition": null,
                "related_terms": [
                    null
                ],
                "standards": [
                    null
                ],
                "date_added": "14/10/2020",
                "date_deprecated": null,
                "version": null,
                "facet": {
                    "cardinalityMax": "1",
                    "ordered": null,
                    "sensitive": null,
                    "transformation": null,
                    "measurementType": null,
                    "measurementUnit": null,
                    "timeZone": null,
                    "codeList": null,
                    "codeType": null
                },
                "type": "float"
            },
            "zCoordinate": {
                "definition": null,
                "related_terms": [
                    null
                ],
                "standards": [
                    null
                ],
                "date_added": "14/10/2020",
                "date_deprecated": null,
                "version": null,
                "facet": {
                    "cardinalityMax": "1",
                    "ordered": null,
                    "sensitive": null,
                    "transformation": null,
                    "measurementType": null,
                    "measurementUnit": null,
                    "timeZone": null,
                    "codeList": null,
                    "codeType": null
                },
                "type": "float"
            },
            "xCoordinate": {
                "definition": null,
                "related_terms": [
                    null
                ],
                "standards": [
                    null
                ],
                "date_added": "14/10/2020",
                "date_deprecated": null,
                "version": null,
                "facet": {
                    "cardinalityMax": null,
                    "ordered": null,
                    "sensitive": null,
                    "transformation": null,
                    "measurementType": null,
                    "measurementUnit": null,
                    "timeZone": null,
                    "codeList": null,
                    "codeType": null
                },
                "type": "float"
            }
        }
    },
    "Line": {
        "definition": null,
        "related_terms": [
            null
        ],
        "standards": [
            null
        ],
        "date_added": "14/10/2020",
        "date_deprecated": null,
        "version": null,
        "children": {
            "Point": {
                "definition": null,
                "related_terms": [
                    null
                ],
                "standards": [
                    null
                ],
                "date_added": "14/10/2020",
                "date_deprecated": null,
                "version": null,
                "facet": {
                    "cardinalityMax": "2",
                    "ordered": null,
                    "sensitive": null,
                    "transformation": null,
                    "measurementType": null,
                    "measurementUnit": null,
                    "timeZone": null,
                    "codeList": null,
                    "codeType": null
                },
                "type": {
                    "$ref": "#/Coordinate3D"
                }
            }
        }
    },
    "Bitmap": {
        "definition": null,
        "related_terms": [
            null
        ],
        "standards": [
            null
        ],
        "date_added": "14/10/2020",
        "date_deprecated": null,
        "version": null,
        "children": {
            "Format": {
                "definition": null,
                "related_terms": [
                    null
                ],
                "standards": [
                    null
                ],
                "date_added": "14/10/2020",
                "date_deprecated": null,
                "version": null,
                "facet": {
                    "cardinalityMax": null,
                    "ordered": null,
                    "sensitive": null,
                    "transformation": null,
                    "measurementType": null,
                    "measurementUnit": null,
                    "timeZone": null,
                    "codeList": null,
                    "codeType": null
                },
                "type": {
                    "$ref": "#/Format"
                }
            },
            "normalVector": {
                "definition": null,
                "related_terms": [
                    null
                ],
                "standards": [
                    null
                ],
                "date_added": "14/10/2020",
                "date_deprecated": null,
                "version": null,
                "facet": {
                    "cardinalityMax": "1",
                    "ordered": null,
                    "sensitive": null,
                    "transformation": null,
                    "measurementType": null,
                    "measurementUnit": null,
                    "timeZone": null,
                    "codeList": null,
                    "codeType": null
                },
                "type": {
                    "$ref": "#/Coordinate3D"
                }
            },
            "reference": {
                "definition": null,
                "related_terms": [
                    null
                ],
                "standards": [
                    null
                ],
                "date_added": "14/10/2020",
                "date_deprecated": null,
                "version": null,
                "facet": {
                    "cardinalityMax": "1",
                    "ordered": null,
                    "sensitive": null,
                    "transformation": null,
                    "measurementType": null,
                    "measurementUnit": null,
                    "timeZone": null,
                    "codeList": null,
                    "codeType": null
                },
                "type": "string"
            },
            "Location": {
                "definition": null,
                "related_terms": [
                    null
                ],
                "standards": [
                    null
                ],
                "date_added": "14/10/2020",
                "date_deprecated": null,
                "version": null,
                "facet": {
                    "cardinalityMax": null,
                    "ordered": null,
                    "sensitive": null,
                    "transformation": null,
                    "measurementType": null,
                    "measurementUnit": null,
                    "timeZone": null,
                    "codeList": null,
                    "codeType": null
                },
                "type": {
                    "$ref": "#/Coordinate3D"
                }
            },
            "upVector": {
                "definition": null,
                "related_terms": [
                    null
                ],
                "standards": [
                    null
                ],
                "date_added": "14/10/2020",
                "date_deprecated": null,
                "version": null,
                "facet": {
                    "cardinalityMax": "1",
                    "ordered": null,
                    "sensitive": null,
                    "transformation": null,
                    "measurementType": null,
                    "measurementUnit": null,
                    "timeZone": null,
                    "codeList": null,
                    "codeType": null
                },
                "type": {
                    "$ref": "#/Coordinate3D"
                }
            }
        }
    },
    "Viewpoint": {
        "definition": null,
        "related_terms": [
            null
        ],
        "standards": [
            null
        ],
        "date_added": "14/10/2020",
        "date_deprecated": null,
        "version": null,
        "children": {
            "snapshotName": {
                "definition": null,
                "related_terms": [
                    null
                ],
                "standards": [
                    null
                ],
                "date_added": "14/10/2020",
                "date_deprecated": null,
                "version": null,
                "facet": {
                    "cardinalityMax": "1",
                    "ordered": null,
                    "sensitive": null,
                    "transformation": null,
                    "measurementType": null,
                    "measurementUnit": null,
                    "timeZone": null,
                    "codeList": null,
                    "codeType": null
                },
                "type": "string"
            },
            "ClippingPlane": {
                "definition": null,
                "related_terms": [
                    null
                ],
                "standards": [
                    null
                ],
                "date_added": "14/10/2020",
                "date_deprecated": null,
                "version": null,
                "facet": {
                    "cardinalityMax": null,
                    "ordered": null,
                    "sensitive": null,
                    "transformation": null,
                    "measurementType": null,
                    "measurementUnit": null,
                    "timeZone": null,
                    "codeList": null,
                    "codeType": null
                },
                "type": {
                    "$ref": "#/ClippingPlane"
                }
            },
            "Camera": {
                "definition": null,
                "related_terms": [
                    null
                ],
                "standards": [
                    null
                ],
                "date_added": "14/10/2020",
                "date_deprecated": null,
                "version": null,
                "facet": {
                    "cardinalityMax": "1",
                    "ordered": null,
                    "sensitive": null,
                    "transformation": null,
                    "measurementType": null,
                    "measurementUnit": null,
                    "timeZone": null,
                    "codeList": null,
                    "codeType": null
                },
                "type": {
                    "$ref": "#/Camera"
                }
            },
            "index": {
                "definition": null,
                "related_terms": [
                    null
                ],
                "standards": [
                    null
                ],
                "date_added": "14/10/2020",
                "date_deprecated": null,
                "version": null,
                "facet": {
                    "cardinalityMax": "1",
                    "ordered": null,
                    "sensitive": null,
                    "transformation": null,
                    "measurementType": null,
                    "measurementUnit": null,
                    "timeZone": null,
                    "codeList": null,
                    "codeType": null
                },
                "type": "integer"
            },
            "Bitmap": {
                "definition": null,
                "related_terms": [
                    null
                ],
                "standards": [
                    null
                ],
                "date_added": "14/10/2020",
                "date_deprecated": null,
                "version": null,
                "facet": {
                    "cardinalityMax": null,
                    "ordered": null,
                    "sensitive": null,
                    "transformation": null,
                    "measurementType": null,
                    "measurementUnit": null,
                    "timeZone": null,
                    "codeList": null,
                    "codeType": null
                },
                "type": {
                    "$ref": "#/Bitmap"
                }
            },
            "relatedToComment": {
                "definition": null,
                "related_terms": [
                    null
                ],
                "standards": [
                    null
                ],
                "date_added": "14/10/2020",
                "date_deprecated": null,
                "version": null,
                "facet": {
                    "cardinalityMax": null,
                    "ordered": null,
                    "sensitive": null,
                    "transformation": null,
                    "measurementType": null,
                    "measurementUnit": null,
                    "timeZone": null,
                    "codeList": null,
                    "codeType": null
                },
                "type": {
                    "$ref": "#/Comment"
                }
            },
            "viewpointName": {
                "definition": null,
                "related_terms": [
                    null
                ],
                "standards": [
                    null
                ],
                "date_added": "14/10/2020",
                "date_deprecated": null,
                "version": null,
                "facet": {
                    "cardinalityMax": "1",
                    "ordered": null,
                    "sensitive": null,
                    "transformation": null,
                    "measurementType": null,
                    "measurementUnit": null,
                    "timeZone": null,
                    "codeList": null,
                    "codeType": null
                },
                "type": "string"
            },
            "Line": {
                "definition": null,
                "related_terms": [
                    null
                ],
                "standards": [
                    null
                ],
                "date_added": "14/10/2020",
                "date_deprecated": null,
                "version": null,
                "facet": {
                    "cardinalityMax": null,
                    "ordered": null,
                    "sensitive": null,
                    "transformation": null,
                    "measurementType": null,
                    "measurementUnit": null,
                    "timeZone": null,
                    "codeList": null,
                    "codeType": null
                },
                "type": {
                    "$ref": "#/Line"
                }
            },
            "identifier": {
                "definition": null,
                "related_terms": [
                    null
                ],
                "standards": [
                    null
                ],
                "date_added": "14/10/2020",
                "date_deprecated": null,
                "version": null,
                "facet": {
                    "cardinalityMax": null,
                    "ordered": null,
                    "sensitive": null,
                    "transformation": null,
                    "measurementType": null,
                    "measurementUnit": null,
                    "timeZone": null,
                    "codeList": null,
                    "codeType": null
                },
                "type": "string"
            },
            "Component": {
                "definition": null,
                "related_terms": [
                    null
                ],
                "standards": [
                    null
                ],
                "date_added": "14/10/2020",
                "date_deprecated": null,
                "version": null,
                "facet": {
                    "cardinalityMax": null,
                    "ordered": null,
                    "sensitive": null,
                    "transformation": null,
                    "measurementType": null,
                    "measurementUnit": null,
                    "timeZone": null,
                    "codeList": null,
                    "codeType": null
                },
                "type": {
                    "$ref": "#/Element"
                }
            }
        }
    },
    "TopicType": {
        "definition": null,
        "related_terms": [
            null
        ],
        "standards": [
            null
        ],
        "date_added": "14/10/2020",
        "date_deprecated": null,
        "version": null,
        "children": {}
    },
    "Camera": {
        "definition": null,
        "related_terms": [
            null
        ],
        "standards": [
            null
        ],
        "date_added": "14/10/2020",
        "date_deprecated": null,
        "version": null,
        "children": {
            "cameraDirection": {
                "definition": null,
                "related_terms": [
                    null
                ],
                "standards": [
                    null
                ],
                "date_added": "14/10/2020",
                "date_deprecated": null,
                "version": null,
                "facet": {
                    "cardinalityMax": null,
                    "ordered": null,
                    "sensitive": null,
                    "transformation": null,
                    "measurementType": null,
                    "measurementUnit": null,
                    "timeZone": null,
                    "codeList": null,
                    "codeType": null
                },
                "type": {
                    "$ref": "#/Coordinate3D"
                }
            },
            "cameraUpVector": {
                "definition": null,
                "related_terms": [
                    null
                ],
                "standards": [
                    null
                ],
                "date_added": "14/10/2020",
                "date_deprecated": null,
                "version": null,
                "facet": {
                    "cardinalityMax": "1",
                    "ordered": null,
                    "sensitive": null,
                    "transformation": null,
                    "measurementType": null,
                    "measurementUnit": null,
                    "timeZone": null,
                    "codeList": null,
                    "codeType": null
                },
                "type": {
                    "$ref": "#/Coordinate3D"
                }
            },
            "cameraViewPoint": {
                "definition": null,
                "related_terms": [
                    null
                ],
                "standards": [
                    null
                ],
                "date_added": "14/10/2020",
                "date_deprecated": null,
                "version": null,
                "facet": {
                    "cardinalityMax": "1",
                    "ordered": null,
                    "sensitive": null,
                    "transformation": null,
                    "measurementType": null,
                    "measurementUnit": null,
                    "timeZone": null,
                    "codeList": null,
                    "codeType": null
                },
                "type": {
                    "$ref": "#/Coordinate3D"
                }
            }
        }
    },
    "PerspectiveCamera": {
        "definition": null,
        "related_terms": [
            null
        ],
        "standards": [
            null
        ],
        "date_added": "14/10/2020",
        "date_deprecated": null,
        "version": null,
        "children": {
            "fieldOfView": {
                "definition": null,
                "related_terms": [
                    null
                ],
                "standards": [
                    null
                ],
                "date_added": "14/10/2020",
                "date_deprecated": null,
                "version": null,
                "facet": {
                    "cardinalityMax": null,
                    "ordered": null,
                    "sensitive": null,
                    "transformation": null,
                    "measurementType": null,
                    "measurementUnit": null,
                    "timeZone": null,
                    "codeList": null,
                    "codeType": null
                },
                "type": "float"
            },
            "cameraDirection": {
                "definition": null,
                "related_terms": [
                    null
                ],
                "standards": [
                    null
                ],
                "date_added": "14/10/2020",
                "date_deprecated": null,
                "version": null,
                "facet": {
                    "cardinalityMax": null,
                    "ordered": null,
                    "sensitive": null,
                    "transformation": null,
                    "measurementType": null,
                    "measurementUnit": null,
                    "timeZone": null,
                    "codeList": null,
                    "codeType": null
                },
                "type": {
                    "$ref": "#/Coordinate3D"
                }
            },
            "cameraUpVector": {
                "definition": null,
                "related_terms": [
                    null
                ],
                "standards": [
                    null
                ],
                "date_added": "14/10/2020",
                "date_deprecated": null,
                "version": null,
                "facet": {
                    "cardinalityMax": "1",
                    "ordered": null,
                    "sensitive": null,
                    "transformation": null,
                    "measurementType": null,
                    "measurementUnit": null,
                    "timeZone": null,
                    "codeList": null,
                    "codeType": null
                },
                "type": {
                    "$ref": "#/Coordinate3D"
                }
            },
            "cameraViewPoint": {
                "definition": null,
                "related_terms": [
                    null
                ],
                "standards": [
                    null
                ],
                "date_added": "14/10/2020",
                "date_deprecated": null,
                "version": null,
                "facet": {
                    "cardinalityMax": "1",
                    "ordered": null,
                    "sensitive": null,
                    "transformation": null,
                    "measurementType": null,
                    "measurementUnit": null,
                    "timeZone": null,
                    "codeList": null,
                    "codeType": null
                },
                "type": {
                    "$ref": "#/Coordinate3D"
                }
            }
        }
    },
    "ClippingPlane": {
        "definition": null,
        "related_terms": [
            null
        ],
        "standards": [
            null
        ],
        "date_added": "14/10/2020",
        "date_deprecated": null,
        "version": null,
        "children": {
            "Direction": {
                "definition": null,
                "related_terms": [
                    null
                ],
                "standards": [
                    null
                ],
                "date_added": "14/10/2020",
                "date_deprecated": null,
                "version": null,
                "facet": {
                    "cardinalityMax": null,
                    "ordered": null,
                    "sensitive": null,
                    "transformation": null,
                    "measurementType": null,
                    "measurementUnit": null,
                    "timeZone": null,
                    "codeList": null,
                    "codeType": null
                },
                "type": {
                    "$ref": "#/Coordinate3D"
                }
            },
            "Location": {
                "definition": null,
                "related_terms": [
                    null
                ],
                "standards": [
                    null
                ],
                "date_added": "14/10/2020",
                "date_deprecated": null,
                "version": null,
                "facet": {
                    "cardinalityMax": "1",
                    "ordered": null,
                    "sensitive": null,
                    "transformation": null,
                    "measurementType": null,
                    "measurementUnit": null,
                    "timeZone": null,
                    "codeList": null,
                    "codeType": null
                },
                "type": {
                    "$ref": "#/Coordinate3D"
                }
            }
        }
    },
    "Comment": {
        "definition": null,
        "related_terms": [
            null
        ],
        "standards": [
            null
        ],
        "date_added": "14/10/2020",
        "date_deprecated": null,
        "version": null,
        "children": {
            "identifier": {
                "definition": null,
                "related_terms": [
                    null
                ],
                "standards": [
                    null
                ],
                "date_added": "14/10/2020",
                "date_deprecated": null,
                "version": null,
                "facet": {
                    "cardinalityMax": null,
                    "ordered": null,
                    "sensitive": null,
                    "transformation": null,
                    "measurementType": null,
                    "measurementUnit": null,
                    "timeZone": null,
                    "codeList": null,
                    "codeType": null
                },
                "type": "string"
            },
            "creationAuthor": {
                "definition": null,
                "related_terms": [
                    null
                ],
                "standards": [
                    null
                ],
                "date_added": "14/10/2020",
                "date_deprecated": null,
                "version": null,
                "facet": {
                    "cardinalityMax": "1",
                    "ordered": null,
                    "sensitive": null,
                    "transformation": null,
                    "measurementType": null,
                    "measurementUnit": null,
                    "timeZone": null,
                    "codeList": null,
                    "codeType": null
                },
                "type": "string"
            },
            "comment": {
                "definition": null,
                "related_terms": [
                    null
                ],
                "standards": [
                    null
                ],
                "date_added": "14/10/2020",
                "date_deprecated": null,
                "version": null,
                "facet": {
                    "cardinalityMax": "1",
                    "ordered": null,
                    "sensitive": null,
                    "transformation": null,
                    "measurementType": null,
                    "measurementUnit": null,
                    "timeZone": null,
                    "codeList": null,
                    "codeType": null
                },
                "type": "string"
            },
            "Viewpoint": {
                "definition": null,
                "related_terms": [
                    null
                ],
                "standards": [
                    null
                ],
                "date_added": "14/10/2020",
                "date_deprecated": null,
                "version": null,
                "facet": {
                    "cardinalityMax": null,
                    "ordered": null,
                    "sensitive": null,
                    "transformation": null,
                    "measurementType": null,
                    "measurementUnit": null,
                    "timeZone": null,
                    "codeList": null,
                    "codeType": null
                },
                "type": {
                    "$ref": "#/Viewpoint"
                }
            },
            "creationDate": {
                "definition": null,
                "related_terms": [
                    null
                ],
                "standards": [
                    null
                ],
                "date_added": "14/10/2020",
                "date_deprecated": null,
                "version": null,
                "facet": {
                    "cardinalityMax": null,
                    "ordered": null,
                    "sensitive": null,
                    "transformation": null,
                    "measurementType": null,
                    "measurementUnit": null,
                    "timeZone": null,
                    "codeList": null,
                    "codeType": null
                },
                "type": "dateTime"
            },
            "modifiedDate": {
                "definition": null,
                "related_terms": [
                    null
                ],
                "standards": [
                    null
                ],
                "date_added": "14/10/2020",
                "date_deprecated": null,
                "version": null,
                "facet": {
                    "cardinalityMax": "1",
                    "ordered": null,
                    "sensitive": null,
                    "transformation": null,
                    "measurementType": null,
                    "measurementUnit": null,
                    "timeZone": null,
                    "codeList": null,
                    "codeType": null
                },
                "type": "dateTime"
            },
            "modifiedAuthor": {
                "definition": null,
                "related_terms": [
                    null
                ],
                "standards": [
                    null
                ],
                "date_added": "14/10/2020",
                "date_deprecated": null,
                "version": null,
                "facet": {
                    "cardinalityMax": "1",
                    "ordered": null,
                    "sensitive": null,
                    "transformation": null,
                    "measurementType": null,
                    "measurementUnit": null,
                    "timeZone": null,
                    "codeList": null,
                    "codeType": null
                },
                "type": "string"
            }
        }
    },
    "Topic": {
        "definition": null,
        "related_terms": [
            null
        ],
        "standards": [
            null
        ],
        "date_added": "14/10/2020",
        "date_deprecated": null,
        "version": null,
        "children": {
            "DocumentReference": {
                "definition": null,
                "related_terms": [
                    null
                ],
                "standards": [
                    null
                ],
                "date_added": "14/10/2020",
                "date_deprecated": null,
                "version": null,
                "facet": {
                    "cardinalityMax": null,
                    "ordered": null,
                    "sensitive": null,
                    "transformation": null,
                    "measurementType": null,
                    "measurementUnit": null,
                    "timeZone": null,
                    "codeList": null,
                    "codeType": null
                },
                "type": {
                    "$ref": "#/InformationObject"
                }
            },
            "TopicType": {
                "definition": null,
                "related_terms": [
                    null
                ],
                "standards": [
                    null
                ],
                "date_added": "14/10/2020",
                "date_deprecated": null,
                "version": null,
                "facet": {
                    "cardinalityMax": "1",
                    "ordered": null,
                    "sensitive": null,
                    "transformation": null,
                    "measurementType": null,
                    "measurementUnit": null,
                    "timeZone": null,
                    "codeList": null,
                    "codeType": null
                },
                "type": {
                    "$ref": "#/TopicType"
                }
            },
            "identifier": {
                "definition": null,
                "related_terms": [
                    null
                ],
                "standards": [
                    null
                ],
                "date_added": "14/10/2020",
                "date_deprecated": null,
                "version": null,
                "facet": {
                    "cardinalityMax": null,
                    "ordered": null,
                    "sensitive": null,
                    "transformation": null,
                    "measurementType": null,
                    "measurementUnit": null,
                    "timeZone": null,
                    "codeList": null,
                    "codeType": null
                },
                "type": "string"
            },
            "priority": {
                "definition": null,
                "related_terms": [
                    null
                ],
                "standards": [
                    null
                ],
                "date_added": "14/10/2020",
                "date_deprecated": null,
                "version": null,
                "facet": {
                    "cardinalityMax": "1",
                    "ordered": null,
                    "sensitive": null,
                    "transformation": null,
                    "measurementType": null,
                    "measurementUnit": null,
                    "timeZone": null,
                    "codeList": null,
                    "codeType": null
                },
                "type": "integer"
            },
            "title": {
                "definition": null,
                "related_terms": [
                    null
                ],
                "standards": [
                    null
                ],
                "date_added": "14/10/2020",
                "date_deprecated": null,
                "version": null,
                "facet": {
                    "cardinalityMax": null,
                    "ordered": null,
                    "sensitive": null,
                    "transformation": null,
                    "measurementType": null,
                    "measurementUnit": null,
                    "timeZone": null,
                    "codeList": null,
                    "codeType": null
                },
                "type": "string"
            },
            "relatedToProject": {
                "definition": null,
                "related_terms": [
                    null
                ],
                "standards": [
                    null
                ],
                "date_added": "14/10/2020",
                "date_deprecated": null,
                "version": null,
                "facet": {
                    "cardinalityMax": null,
                    "ordered": null,
                    "sensitive": null,
                    "transformation": null,
                    "measurementType": null,
                    "measurementUnit": null,
                    "timeZone": null,
                    "codeList": null,
                    "codeType": null
                },
                "type": {
                    "$ref": "#/Project"
                }
            },
            "Comment": {
                "definition": null,
                "related_terms": [
                    null
                ],
                "standards": [
                    null
                ],
                "date_added": "14/10/2020",
                "date_deprecated": null,
                "version": null,
                "facet": {
                    "cardinalityMax": null,
                    "ordered": null,
                    "sensitive": null,
                    "transformation": null,
                    "measurementType": null,
                    "measurementUnit": null,
                    "timeZone": null,
                    "codeList": null,
                    "codeType": null
                },
                "type": {
                    "$ref": "#/Comment"
                }
            },
            "File": {
                "definition": null,
                "related_terms": [
                    null
                ],
                "standards": [
                    null
                ],
                "date_added": "14/10/2020",
                "date_deprecated": null,
                "version": null,
                "facet": {
                    "cardinalityMax": null,
                    "ordered": null,
                    "sensitive": null,
                    "transformation": null,
                    "measurementType": null,
                    "measurementUnit": null,
                    "timeZone": null,
                    "codeList": null,
                    "codeType": null
                },
                "type": {
                    "$ref": "#/InformationObject"
                }
            },
            "creationAuthor": {
                "definition": null,
                "related_terms": [
                    null
                ],
                "standards": [
                    null
                ],
                "date_added": "14/10/2020",
                "date_deprecated": null,
                "version": null,
                "facet": {
                    "cardinalityMax": null,
                    "ordered": null,
                    "sensitive": null,
                    "transformation": null,
                    "measurementType": null,
                    "measurementUnit": null,
                    "timeZone": null,
                    "codeList": null,
                    "codeType": null
                },
                "type": "string"
            },
            "dueDate": {
                "definition": null,
                "related_terms": [
                    null
                ],
                "standards": [
                    null
                ],
                "date_added": "14/10/2020",
                "date_deprecated": null,
                "version": null,
                "facet": {
                    "cardinalityMax": "1",
                    "ordered": null,
                    "sensitive": null,
                    "transformation": null,
                    "measurementType": null,
                    "measurementUnit": null,
                    "timeZone": null,
                    "codeList": null,
                    "codeType": null
                },
                "type": "dateTime"
            },
            "creationDate": {
                "definition": null,
                "related_terms": [
                    null
                ],
                "standards": [
                    null
                ],
                "date_added": "14/10/2020",
                "date_deprecated": null,
                "version": null,
                "facet": {
                    "cardinalityMax": "1",
                    "ordered": null,
                    "sensitive": null,
                    "transformation": null,
                    "measurementType": null,
                    "measurementUnit": null,
                    "timeZone": null,
                    "codeList": null,
                    "codeType": null
                },
                "type": "dateTime"
            },
            "ReferenceLink": {
                "definition": null,
                "related_terms": [
                    null
                ],
                "standards": [
                    null
                ],
                "date_added": "14/10/2020",
                "date_deprecated": null,
                "version": null,
                "facet": {
                    "cardinalityMax": null,
                    "ordered": null,
                    "sensitive": null,
                    "transformation": null,
                    "measurementType": null,
                    "measurementUnit": null,
                    "timeZone": null,
                    "codeList": null,
                    "codeType": null
                },
                "type": {
                    "$ref": "#/InformationObject"
                }
            },
            "BimSnippet": {
                "definition": null,
                "related_terms": [
                    null
                ],
                "standards": [
                    null
                ],
                "date_added": "14/10/2020",
                "date_deprecated": null,
                "version": null,
                "facet": {
                    "cardinalityMax": null,
                    "ordered": null,
                    "sensitive": null,
                    "transformation": null,
                    "measurementType": null,
                    "measurementUnit": null,
                    "timeZone": null,
                    "codeList": null,
                    "codeType": null
                },
                "type": {
                    "$ref": "#/InformationObject"
                }
            },
            "description": {
                "definition": null,
                "related_terms": [
                    null
                ],
                "standards": [
                    null
                ],
                "date_added": "14/10/2020",
                "date_deprecated": null,
                "version": null,
                "facet": {
                    "cardinalityMax": "1",
                    "ordered": null,
                    "sensitive": null,
                    "transformation": null,
                    "measurementType": null,
                    "measurementUnit": null,
                    "timeZone": null,
                    "codeList": null,
                    "codeType": null
                },
                "type": "string"
            },
            "TopicStatus": {
                "definition": null,
                "related_terms": [
                    null
                ],
                "standards": [
                    null
                ],
                "date_added": "14/10/2020",
                "date_deprecated": null,
                "version": null,
                "facet": {
                    "cardinalityMax": "1",
                    "ordered": null,
                    "sensitive": null,
                    "transformation": null,
                    "measurementType": null,
                    "measurementUnit": null,
                    "timeZone": null,
                    "codeList": null,
                    "codeType": null
                },
                "type": {
                    "$ref": "#/TopicStatus"
                }
            },
            "modifiedAuthor": {
                "definition": null,
                "related_terms": [
                    null
                ],
                "standards": [
                    null
                ],
                "date_added": "14/10/2020",
                "date_deprecated": null,
                "version": null,
                "facet": {
                    "cardinalityMax": "1",
                    "ordered": null,
                    "sensitive": null,
                    "transformation": null,
                    "measurementType": null,
                    "measurementUnit": null,
                    "timeZone": null,
                    "codeList": null,
                    "codeType": null
                },
                "type": "string"
            },
            "Stage": {
                "definition": null,
                "related_terms": [
                    null
                ],
                "standards": [
                    null
                ],
                "date_added": "14/10/2020",
                "date_deprecated": null,
                "version": null,
                "facet": {
                    "cardinalityMax": "1",
                    "ordered": null,
                    "sensitive": null,
                    "transformation": null,
                    "measurementType": null,
                    "measurementUnit": null,
                    "timeZone": null,
                    "codeList": null,
                    "codeType": null
                },
                "type": {
                    "$ref": "#/Stage"
                }
            },
            "modifiedDate": {
                "definition": null,
                "related_terms": [
                    null
                ],
                "standards": [
                    null
                ],
                "date_added": "14/10/2020",
                "date_deprecated": null,
                "version": null,
                "facet": {
                    "cardinalityMax": "1",
                    "ordered": null,
                    "sensitive": null,
                    "transformation": null,
                    "measurementType": null,
                    "measurementUnit": null,
                    "timeZone": null,
                    "codeList": null,
                    "codeType": null
                },
                "type": "dateTime"
            },
            "index": {
                "definition": null,
                "related_terms": [
                    null
                ],
                "standards": [
                    null
                ],
                "date_added": "14/10/2020",
                "date_deprecated": null,
                "version": null,
                "facet": {
                    "cardinalityMax": "1",
                    "ordered": null,
                    "sensitive": null,
                    "transformation": null,
                    "measurementType": null,
                    "measurementUnit": null,
                    "timeZone": null,
                    "codeList": null,
                    "codeType": null
                },
                "type": "integer"
            },
            "assignedTo": {
                "definition": null,
                "related_terms": [
                    null
                ],
                "standards": [
                    null
                ],
                "date_added": "14/10/2020",
                "date_deprecated": null,
                "version": null,
                "facet": {
                    "cardinalityMax": "1",
                    "ordered": null,
                    "sensitive": null,
                    "transformation": null,
                    "measurementType": null,
                    "measurementUnit": null,
                    "timeZone": null,
                    "codeList": null,
                    "codeType": null
                },
                "type": "string"
            }
        }
    },
    "TopicLabel": {
        "definition": null,
        "related_terms": [
            null
        ],
        "standards": [
            null
        ],
        "date_added": "14/10/2020",
        "date_deprecated": null,
        "version": null,
        "children": {}
    },
    "Stage": {
        "definition": null,
        "related_terms": [
            null
        ],
        "standards": [
            null
        ],
        "date_added": "14/10/2020",
        "date_deprecated": null,
        "version": null,
        "children": {}
    },
    "Element": {
        "definition": null,
        "related_terms": [
            null
        ],
        "standards": [
            null
        ],
        "date_added": "06/11/2020",
        "date_deprecated": null,
        "version": null,
        "children": {
            "autoringToolId": {
                "definition": null,
                "related_terms": [
                    null
                ],
                "standards": [
                    null
                ],
                "date_added": null,
                "date_deprecated": null,
                "version": null,
                "facet": {
                    "cardinalityMax": "1",
                    "ordered": null,
                    "sensitive": null,
                    "transformation": null,
                    "measurementType": null,
                    "measurementUnit": null,
                    "timeZone": null,
                    "codeList": null,
                    "codeType": null
                },
                "type": "string"
            },
            "originatingSystem": {
                "definition": null,
                "related_terms": [
                    null
                ],
                "standards": [
                    null
                ],
                "date_added": "14/10/2020",
                "date_deprecated": null,
                "version": null,
                "facet": {
                    "cardinalityMax": "1",
                    "ordered": null,
                    "sensitive": null,
                    "transformation": null,
                    "measurementType": null,
                    "measurementUnit": null,
                    "timeZone": null,
                    "codeList": null,
                    "codeType": null
                },
                "type": "string"
            },
            "ifcIdentifier": {
                "definition": null,
                "related_terms": [
                    null
                ],
                "standards": [
                    null
                ],
                "date_added": "06/11/2020",
                "date_deprecated": null,
                "version": null,
                "facet": {
                    "cardinalityMax": "1",
                    "ordered": null,
                    "sensitive": null,
                    "transformation": null,
                    "measurementType": null,
                    "measurementUnit": null,
                    "timeZone": null,
                    "codeList": null,
                    "codeType": null
                },
                "type": "string"
            },
            "colorDisplay": {
                "definition": null,
                "related_terms": [
                    null
                ],
                "standards": [
                    null
                ],
                "date_added": "14/10/2020",
                "date_deprecated": null,
                "version": null,
                "facet": {
                    "cardinalityMax": "1",
                    "ordered": null,
                    "sensitive": null,
                    "transformation": null,
                    "measurementType": null,
                    "measurementUnit": null,
                    "timeZone": null,
                    "codeList": null,
                    "codeType": null
                },
                "type": "string"
            }
        }
    },
    "Format": {
        "definition": null,
        "related_terms": [
            null
        ],
        "standards": [
            null
        ],
        "date_added": "06/11/2020",
        "date_deprecated": null,
        "version": null,
        "children": {}
    },
    "TopicStatus": {
        "definition": null,
        "related_terms": [
            null
        ],
        "standards": [
            null
        ],
        "date_added": "14/10/2020",
        "date_deprecated": null,
        "version": null,
        "children": {}
    },
    "OrthogonalCamera": {
        "definition": null,
        "related_terms": [
            null
        ],
        "standards": [
            null
        ],
        "date_added": "14/10/2020",
        "date_deprecated": null,
        "version": null,
        "children": {
            "viewToWorldScale": {
                "definition": null,
                "related_terms": [
                    null
                ],
                "standards": [
                    null
                ],
                "date_added": "14/10/2020",
                "date_deprecated": null,
                "version": null,
                "facet": {
                    "cardinalityMax": "1",
                    "ordered": null,
                    "sensitive": null,
                    "transformation": null,
                    "measurementType": null,
                    "measurementUnit": null,
                    "timeZone": null,
                    "codeList": null,
                    "codeType": null
                },
                "type": "float"
            },
            "cameraDirection": {
                "definition": null,
                "related_terms": [
                    null
                ],
                "standards": [
                    null
                ],
                "date_added": "14/10/2020",
                "date_deprecated": null,
                "version": null,
                "facet": {
                    "cardinalityMax": null,
                    "ordered": null,
                    "sensitive": null,
                    "transformation": null,
                    "measurementType": null,
                    "measurementUnit": null,
                    "timeZone": null,
                    "codeList": null,
                    "codeType": null
                },
                "type": {
                    "$ref": "#/Coordinate3D"
                }
            },
            "cameraUpVector": {
                "definition": null,
                "related_terms": [
                    null
                ],
                "standards": [
                    null
                ],
                "date_added": "14/10/2020",
                "date_deprecated": null,
                "version": null,
                "facet": {
                    "cardinalityMax": "1",
                    "ordered": null,
                    "sensitive": null,
                    "transformation": null,
                    "measurementType": null,
                    "measurementUnit": null,
                    "timeZone": null,
                    "codeList": null,
                    "codeType": null
                },
                "type": {
                    "$ref": "#/Coordinate3D"
                }
            },
            "cameraViewPoint": {
                "definition": null,
                "related_terms": [
                    null
                ],
                "standards": [
                    null
                ],
                "date_added": "14/10/2020",
                "date_deprecated": null,
                "version": null,
                "facet": {
                    "cardinalityMax": "1",
                    "ordered": null,
                    "sensitive": null,
                    "transformation": null,
                    "measurementType": null,
                    "measurementUnit": null,
                    "timeZone": null,
                    "codeList": null,
                    "codeType": null
                },
                "type": {
                    "$ref": "#/Coordinate3D"
                }
            }
        }
    },
    "Project": {
        "definition": null,
        "related_terms": [
            null
        ],
        "standards": [
            null
        ],
        "date_added": "06/11/2020",
        "date_deprecated": null,
        "version": null,
        "children": {
            "identifier": {
                "definition": null,
                "related_terms": [
                    null
                ],
                "standards": [
                    null
                ],
                "date_added": "06/11/2020",
                "date_deprecated": null,
                "version": null,
                "facet": {
                    "cardinalityMax": null,
                    "ordered": null,
                    "sensitive": null,
                    "transformation": null,
                    "measurementType": null,
                    "measurementUnit": null,
                    "timeZone": null,
                    "codeList": null,
                    "codeType": null
                },
                "type": "string"
            }
        }
    },
    "InformationObject": {
        "definition": null,
        "related_terms": [
            null
        ],
        "standards": [
            null
        ],
        "date_added": "06/11/2020",
        "date_deprecated": null,
        "version": null,
        "children": {
            "Extension": {
                "definition": null,
                "related_terms": [
                    null
                ],
                "standards": [
                    null
                ],
                "date_added": null,
                "date_deprecated": null,
                "version": null,
                "facet": {
                    "cardinalityMax": "1",
                    "ordered": null,
                    "sensitive": null,
                    "transformation": null,
                    "measurementType": null,
                    "measurementUnit": null,
                    "timeZone": null,
                    "codeList": null,
                    "codeType": null
                },
                "type": {
                    "$ref": "#/Format"
                }
            }
        }
    }
}